rtl/isa_defs.vh
// архитектура набора команд
`ifndef ISA_DEFS_VH
`define ISA_DEFS_VH

`define OP_ADD   4'b0001
`define OP_SUB   4'b0010
`define OP_AND   4'b0011
`define OP_OR    4'b0100
`define OP_LOAD  4'b0101
`define OP_STORE 4'b0110
`define OP_LDI   4'b0111
`define OP_JUMP  4'b1000
`define OP_BEQ   4'b1001
`define OP_XOR   4'b1010
`define OP_NOT   4'b1011

`define ALU_ADD    4'b0001
`define ALU_SUB    4'b0010
`define ALU_AND    4'b0011
`define ALU_OR     4'b0100
`define ALU_XOR    4'b1010
`define ALU_NOT    4'b1011
`define ALU_PASS_A 4'b1100
`define ALU_PASS_B 4'b1101

`endif

rtl/control_unit.v
// Файл: rtl/control_unit.v
`include "isa_defs.vh"

module control_unit (
    input  wire        clk,
    input  wire        rst_n,
    input  wire [15:0] instruction,  // Текущая команда из instr_mem
    input  wire        zero_flag,    // Флаг из АЛУ
    // Управляющие сигналы для Data Path
    output reg         pc_load,
    output reg  [15:0] pc_next,
    output reg         reg_write,
    output reg         mem_write,
    output reg  [3:0]  alu_op,
    output reg         alu_src_b_sel, // Выбор между регистром и Immediate
    output reg  [1:0]  state_debug
);
    localparam FETCH_STATE   = 2'b00;
    localparam EXECUTE_STATE = 2'b01;

    wire [3:0] opcode = instruction[15:12];

    // Регистр состояний FSM (переходы Moore: только от текущего state)
    always @(posedge clk or negedge rst_n) begin
        if (!rst_n)
            state_debug <= FETCH_STATE;
        else if (state_debug == FETCH_STATE)
            state_debug <= EXECUTE_STATE;
        else
            state_debug <= FETCH_STATE;
    end

    // Комбинационная логика выходов (Mealy: opcode, zero_flag; см. PROJECT_REQUIREMENTS_COMPLIANCE.txt)
    always @(*) begin
        pc_load = 1'b0;
        pc_next = 16'd0;
        reg_write = 1'b0;
        mem_write = 1'b0;
        alu_op = `ALU_ADD;
        alu_src_b_sel = 1'b0;

        case (opcode)
            `OP_ADD: begin
                reg_write = 1'b1;
                alu_op = `ALU_ADD;
            end
            `OP_SUB: begin
                reg_write = 1'b1;
                alu_op = `ALU_SUB;
            end
            `OP_AND: begin
                reg_write = 1'b1;
                alu_op = `ALU_AND;
            end
            `OP_OR: begin
                reg_write = 1'b1;
                alu_op = `ALU_OR;
            end
            `OP_XOR: begin
                reg_write = 1'b1;
                alu_op = `ALU_XOR;
            end
            `OP_NOT: begin
                reg_write = 1'b1;
                alu_op = `ALU_NOT;
            end
            `OP_LOAD: begin
                reg_write = 1'b1;
                alu_op = `ALU_ADD;
                alu_src_b_sel = 1'b1;
            end
            `OP_STORE: begin
                mem_write = 1'b1;
                alu_op = `ALU_ADD;
                alu_src_b_sel = 1'b1;
            end
            `OP_LDI: begin
                reg_write = 1'b1;
                alu_op = `ALU_PASS_B;
            end
            `OP_JUMP: begin
                pc_load = 1'b1;
                pc_next = {4'd0, instruction[11:0]};
            end
            `OP_BEQ: begin
                if (zero_flag) begin
                    pc_load = 1'b1;
                    pc_next = {4'd0, instruction[11:0]};
                end
            end
            default: begin
                // NOP
            end
        endcase
    end

endmodule

tb/tb_control_unit.v
`timescale 1ns / 1ps
`include "../rtl/isa_defs.vh"

module tb_control_unit;

    reg        clk, rst_n;
    reg [15:0] instruction;
    reg        zero_flag;
    wire       pc_load;
    wire [15:0] pc_next;
    wire       reg_write, mem_write;
    wire [3:0] alu_op;
    wire       alu_src_b_sel;
    wire [1:0] state_debug;

    control_unit uut (
        .clk(clk),
        .rst_n(rst_n),
        .instruction(instruction),
        .zero_flag(zero_flag),
        .pc_load(pc_load),
        .pc_next(pc_next),
        .reg_write(reg_write),
        .mem_write(mem_write),
        .alu_op(alu_op),
        .alu_src_b_sel(alu_src_b_sel),
        .state_debug(state_debug)
    );

    always #5 clk = ~clk;

    // Задача для подачи инструкции и наблюдения за проходом FSM
    task test_instruction;
        input [15:0] instr;
        input        expected_reg_write;
        input        expected_mem_write;
        input [3:0]  expected_alu_op;
        begin
            instruction = instr;
            zero_flag = 1'b0;
            $display("[CTRL] apply instruction=0x%04h", instr);
            // Ждем, пока FSM пройдет до WRITE_BACK/FETCH (достаточно 4 тактов)
            repeat(4) @(posedge clk);
            #1;
            $display("[CTRL] outputs: reg_write=%b mem_write=%b alu_op=0x%0h alu_src_b_sel=%b pc_load=%b pc_next=0x%04h state=%0d",
                     reg_write, mem_write, alu_op, alu_src_b_sel, pc_load, pc_next, state_debug);
            // Проверки
            if (reg_write !== expected_reg_write)
                $error("reg_write mismatch for instr %h", instr);
            if (mem_write !== expected_mem_write)
                $error("mem_write mismatch for instr %h", instr);
            if (alu_op !== expected_alu_op)
                $error("alu_op mismatch for instr %h", instr);
        end
    endtask

    initial begin
        $dumpfile("sim/tb_control_unit.vcd");
        $dumpvars(0, tb_control_unit);

        $display("=== Control unit test start ===");
        $display("Block purpose: decodes opcode and generates control signals for the datapath.");
        $display("Signals of interest: reg_write, mem_write, alu_op, alu_src_b_sel, pc_load, pc_next.");

        clk = 0; rst_n = 0; instruction = 16'h0000; zero_flag = 0;
        #10 rst_n = 1;

        // Тест команды ADD R1,R2,R3
        $display("[CTRL] expected behavior for ADD: write result to register, ALU performs ADD.");
        test_instruction(16'b0001_001_010_011_000, 1'b1, 1'b0, `ALU_ADD);

        // Тест LOAD R4, [R5 + imm6]
        $display("[CTRL] expected behavior for LOAD: address via ALU add, then register write enabled.");
        test_instruction(16'b0101_100_101_000_001, 1'b1, 1'b0, `ALU_ADD);

        // Тест STORE R6, [R7 + imm6]
        $display("[CTRL] expected behavior for STORE: address via ALU add, then memory write enabled.");
        test_instruction(16'b0110_110_111_000_001, 1'b0, 1'b1, `ALU_ADD);

        // Тест JUMP immediate (опкод 4'b1000)
        instruction = 16'b1000_000_000_000_000; // адрес 0
        zero_flag = 0;
        @(posedge clk); // DECODE должен активировать pc_load
        #1;
        $display("[CTRL] JUMP outputs: pc_load=%b pc_next=0x%04h state=%0d",
                 pc_load, pc_next, state_debug);
        if (pc_load !== 1'b1) $error("JUMP should set pc_load");

        $display("Control unit tests completed.");
        $finish;
    end

endmodule

sim/tb_control_unit.vcd
$date
	Wed May 27 14:03:13 2026
$end
$version
	Icarus Verilog
$end
$timescale
	1ps
$end
$scope module tb_control_unit $end
$var wire 2 ! state_debug [1:0] $end
$var wire 1 " reg_write $end
$var wire 16 # pc_next [15:0] $end
$var wire 1 $ pc_load $end
$var wire 1 % mem_write $end
$var wire 1 & alu_src_b_sel $end
$var wire 4 ' alu_op [3:0] $end
$var reg 1 ( clk $end
$var reg 16 ) instruction [15:0] $end
$var reg 1 * rst_n $end
$var reg 1 + zero_flag $end
$scope module uut $end
$var wire 1 ( clk $end
$var wire 16 , instruction [15:0] $end
$var wire 1 * rst_n $end
$var wire 1 + zero_flag $end
$var wire 4 - opcode [3:0] $end
$var parameter 2 . EXECUTE_STATE $end
$var parameter 2 / FETCH_STATE $end
$var reg 4 0 alu_op [3:0] $end
$var reg 1 & alu_src_b_sel $end
$var reg 1 % mem_write $end
$var reg 1 $ pc_load $end
$var reg 16 1 pc_next [15:0] $end
$var reg 1 " reg_write $end
$var reg 2 2 state_debug [1:0] $end
$upscope $end
$scope task test_instruction $end
$var reg 4 3 expected_alu_op [3:0] $end
$var reg 1 4 expected_mem_write $end
$var reg 1 5 expected_reg_write $end
$var reg 16 6 instr [15:0] $end
$upscope $end
$upscope $end
$enddefinitions $end
$comment Show the parameter values. $end
$dumpall
b0 /
b1 .
$end
#0
$dumpvars
bx 6
x5
x4
bx 3
b0 2
b0 1
b1 0
b0 -
b0 ,
0+
0*
b0 )
0(
b1 '
0&
0%
0$
b0 #
0"
b0 !
$end
#5000
1(
#10000
1"
b1 -
0(
b1001010011000 )
b1001010011000 ,
b1 3
04
15
b1001010011000 6
1*
#15000
b1 !
b1 2
1(
#20000
0(
#25000
b0 !
b0 2
1(
#30000
0(
#35000
b1 !
b1 2
1(
#40000
0(
#45000
b0 !
b0 2
1(
#46000
1&
1"
b101 -
b101100101000001 )
b101100101000001 ,
b101100101000001 6
#50000
0(
#55000
b1 !
b1 2
1(
#60000
0(
#65000
b0 !
b0 2
1(
#70000
0(
#75000
b1 !
b1 2
1(
#80000
0(
#85000
b0 !
b0 2
1(
#86000
1%
1&
0"
b110 -
b110110111000001 )
b110110111000001 ,
14
05
b110110111000001 6
#90000
0(
#95000
b1 !
b1 2
1(
#100000
0(
#105000
b0 !
b0 2
1(
#110000
0(
#115000
b1 !
b1 2
1(
#120000
0(
#125000
b0 !
b0 2
1(
#126000
1$
0&
0%
b1000 -
b1000000000000000 )
b1000000000000000 ,
#130000
0(
#135000
b1 !
b1 2
1(
