rtl/pc.v
// Файл: rtl/pc.v
module program_counter (
    input  wire        clk,
    input  wire        rst_n,      // Асинхронный сброс (активный 0)
    input  wire        pc_load,    // Сигнал загрузки нового адреса (от FSM)
    input  wire [15:0] pc_next,    // Новый адрес перехода
    output reg  [15:0] pc_current  // Текущий адрес команды
);

    // Асинхронный сброс, синхронное обновление
    always @(posedge clk or negedge rst_n) begin
        if (!rst_n) // если rst_n = 0, сброс счетчика команд. rst = reset
            pc_current <= 16'h0000;   // Старт с адреса 0
        else if (pc_load)
            pc_current <= pc_next;
        else
            pc_current <= pc_current + 16'd1; // Линейное выполнение
    end

endmodule

tb/tb_pc.v
`timescale 1ns / 1ps

module tb_pc;

    reg        clk, rst_n, pc_load;
    reg [15:0] pc_next;
    wire [15:0] pc_current;

    program_counter uut (
        .clk(clk),
        .rst_n(rst_n),
        .pc_load(pc_load),
        .pc_next(pc_next),
        .pc_current(pc_current)
    );

    // Генерация тактов (период 10 нс)
    always #5 clk = ~clk;

    initial begin
        $dumpfile("sim/tb_pc.vcd");
        $dumpvars(0, tb_pc);

        $display("=== PC test start ===");
        $display("Block purpose: program counter stores current instruction address.");
        $display("Signals: rst_n resets PC, pc_load loads jump target, pc_next is jump address.");

        clk = 0; rst_n = 0; pc_load = 0; pc_next = 0;
        #1;
        $display("[PC] reset active: rst_n=%b pc_load=%b pc_next=0x%04h pc_current=0x%04h",
                 rst_n, pc_load, pc_next, pc_current);
        if (pc_current !== 0) $error("Reset failed while reset is active");

        #9 rst_n = 1; // снимаем сброс
        #1;
        $display("[PC] reset released: rst_n=%b pc_current=0x%04h", rst_n, pc_current);
        if (pc_current !== 0) $error("PC changed too early after reset release");

        // Проверка инкремента
        @(posedge clk); #1;
        $display("[PC] increment step 1: pc_current=0x%04h (%0d)", pc_current, pc_current);
        if (pc_current !== 1) $error("Increment failed");
        @(posedge clk); #1;
        $display("[PC] increment step 2: pc_current=0x%04h (%0d)", pc_current, pc_current);
        if (pc_current !== 2) $error("Increment failed");

        // Проверка загрузки (JUMP)
        pc_load = 1; pc_next = 16'h0042;
        $display("[PC] request jump: pc_load=%b pc_next=0x%04h", pc_load, pc_next);
        @(posedge clk); #1; pc_load = 0;
        $display("[PC] after jump load: pc_current=0x%04h (%0d)", pc_current, pc_current);
        if (pc_current !== 16'h0042) $error("Jump load failed");

        // Проверка инкремента после загрузки
        @(posedge clk); #1;
        $display("[PC] increment after jump: pc_current=0x%04h (%0d)", pc_current, pc_current);
        if (pc_current !== 16'h0043) $error("Post-jump increment failed");

        $display("PC tests completed.");
        $finish;
    end

endmodule

sim/tb_pc.vcd
$date
	Sat Apr 11 18:38:20 2026
$end
$version
	Icarus Verilog
$end
$timescale
	1ps
$end
$scope module tb_pc $end
$var wire 16 ! pc_current [15:0] $end
$var reg 1 " clk $end
$var reg 1 # pc_load $end
$var reg 16 $ pc_next [15:0] $end
$var reg 1 % rst_n $end
$scope module uut $end
$var wire 1 " clk $end
$var wire 1 # pc_load $end
$var wire 16 & pc_next [15:0] $end
$var wire 1 % rst_n $end
$var reg 16 ' pc_current [15:0] $end
$upscope $end
$upscope $end
$enddefinitions $end
$comment Show the parameter values. $end
$dumpall
$end
#0
$dumpvars
b0 '
b0 &
0%
b0 $
0#
0"
b0 !
$end
#5000
1"
#10000
0"
1%
#15000
b1 !
b1 '
1"
#20000
0"
#25000
b10 !
b10 '
1"
#26000
b1000010 $
b1000010 &
1#
#30000
0"
#35000
b1000010 !
b1000010 '
1"
#36000
0#
#40000
0"
#45000
b1000011 !
b1000011 '
1"
