rtl/reg_file.v
// Файл: rtl/reg_file.v
module register_file (
    input  wire        clk,
    input  wire        rst_n,
    input  wire        reg_write,        // Разрешение записи (от FSM)
    input  wire [2:0]  read_addr1,       // Адрес первого операнда (SR1)
    input  wire [2:0]  read_addr2,       // Адрес второго операнда (SR2)
    input  wire [2:0]  write_addr,       // Адрес для записи (DR)
    input  wire [15:0] write_data,       // Данные для записи
    output wire [15:0] read_data1,       // Значение первого операнда
    output wire [15:0] read_data2        // Значение второго операнда
);

    // Память регистров (8 x 16 бит)
    reg [15:0] registers [0:7];
    
    // Запись (синхронная)
    always @(posedge clk or negedge rst_n) begin
        if (!rst_n) begin
            // Сброс всех регистров (можно обнулить, но R0 всегда 0 аппаратно)
            integer i;
            for (i = 0; i < 8; i = i + 1)
                registers[i] <= 16'd0;
        end else if (reg_write && write_addr != 3'd0) begin
            // Запрещаем запись в R0
            registers[write_addr] <= write_data;
        end
    end
    
    // Чтение (асинхронное, комбинационное)
    assign read_data1 = (read_addr1 == 3'd0) ? 16'd0 : registers[read_addr1];
    assign read_data2 = (read_addr2 == 3'd0) ? 16'd0 : registers[read_addr2];

    // Пробные сигналы для VCD/GTKWave (массив registers в .vcd не всегда виден)
    wire [15:0] dbg_r1 = registers[1];
    wire [15:0] dbg_r2 = registers[2];
    wire [15:0] dbg_r3 = registers[3];
    wire [15:0] dbg_r7 = registers[7];

endmodule

tb/tb_reg_file.v
`timescale 1ns / 1ps

module tb_reg_file;

    reg        clk, rst_n, reg_write;
    reg [2:0]  read_addr1, read_addr2, write_addr;
    reg [15:0] write_data;
    wire [15:0] read_data1, read_data2;

    register_file uut (
        .clk(clk),
        .rst_n(rst_n),
        .reg_write(reg_write),
        .read_addr1(read_addr1),
        .read_addr2(read_addr2),
        .write_addr(write_addr),
        .write_data(write_data),
        .read_data1(read_data1),
        .read_data2(read_data2)
    );

    always #5 clk = ~clk;

    initial begin
        $dumpfile("sim/tb_reg_file.vcd");
        $dumpvars(0, tb_reg_file);

        $display("=== Register file test start ===");
        $display("Block purpose: stores 8 general-purpose registers and serves two read ports plus one write port.");

        clk = 0; rst_n = 0; reg_write = 0;
        read_addr1 = 0; read_addr2 = 0; write_addr = 0; write_data = 0;
        #10 rst_n = 1;
        $display("[REG] reset released. All registers must be zero.");

        // Проверка: R0 всегда читается как 0
        read_addr1 = 3'd0; #1;
        $display("[REG] read R0 -> 0x%04h", read_data1);
        if (read_data1 !== 0) $error("R0 read not zero");

        // Запись в R1 значения 0x1234
        @(posedge clk);
        reg_write = 1; write_addr = 3'd1; write_data = 16'h1234;
        $display("[REG] write request: reg_write=%b write_addr=R%0d write_data=0x%04h",
                 reg_write, write_addr, write_data);
        @(posedge clk);
        reg_write = 0;

        // Чтение R1 (асинхронно)
        read_addr1 = 3'd1; #1;
        $display("[REG] read R1 -> 0x%04h", read_data1);
        if (read_data1 !== 16'h1234) $error("Write/read to R1 failed");

        // Проверка одновременного чтения двух портов
        read_addr1 = 3'd1; read_addr2 = 3'd2;
        @(posedge clk); // запись в R2
        reg_write = 1; write_addr = 3'd2; write_data = 16'h5678;
        $display("[REG] write request: reg_write=%b write_addr=R%0d write_data=0x%04h",
                 reg_write, write_addr, write_data);
        @(posedge clk);
        reg_write = 0;
        #1; // даем комбинационному чтению обновиться
        $display("[REG] dual read: R1=0x%04h R2=0x%04h", read_data1, read_data2);
        if (read_data1 !== 16'h1234 || read_data2 !== 16'h5678) $error("Dual read failed");

        // Попытка записи в R0 (не должна сработать)
        @(posedge clk);
        reg_write = 1; write_addr = 3'd0; write_data = 16'hAAAA;
        $display("[REG] forbidden write request: write_addr=R0 write_data=0x%04h", write_data);
        @(posedge clk);
        reg_write = 0;
        read_addr1 = 3'd0; #1;
        $display("[REG] read R0 after forbidden write -> 0x%04h", read_data1);
        if (read_data1 !== 0) $error("Write to R0 should be ignored");

        $display("Register file tests completed.");
        $finish;
    end

endmodule

sim/tb_reg_file.vcd
$date
	Thu May 28 21:30:41 2026
$end
$version
	Icarus Verilog
$end
$timescale
	1ps
$end
$scope module tb_reg_file $end
$var wire 16 ! read_data2 [15:0] $end
$var wire 16 " read_data1 [15:0] $end
$var reg 1 # clk $end
$var reg 3 $ read_addr1 [2:0] $end
$var reg 3 % read_addr2 [2:0] $end
$var reg 1 & reg_write $end
$var reg 1 ' rst_n $end
$var reg 3 ( write_addr [2:0] $end
$var reg 16 ) write_data [15:0] $end
$scope module uut $end
$var wire 1 # clk $end
$var wire 16 * dbg_r1 [15:0] $end
$var wire 16 + dbg_r3 [15:0] $end
$var wire 16 , dbg_r7 [15:0] $end
$var wire 3 - read_addr1 [2:0] $end
$var wire 3 . read_addr2 [2:0] $end
$var wire 1 & reg_write $end
$var wire 1 ' rst_n $end
$var wire 3 / write_addr [2:0] $end
$var wire 16 0 write_data [15:0] $end
$var wire 16 1 read_data2 [15:0] $end
$var wire 16 2 read_data1 [15:0] $end
$scope begin $unm_blk_3 $end
$var integer 32 3 i [31:0] $end
$upscope $end
$upscope $end
$upscope $end
$enddefinitions $end
$comment Show the parameter values. $end
$dumpall
$end
#0
$dumpvars
b1000 3
b0 2
b0 1
b0 0
b0 /
b0 .
b0 -
b0 ,
b0 +
b0 *
b0 )
b0 (
0'
0&
b0 %
b0 $
0#
b0 "
b0 !
$end
#5000
b1000 3
1#
#10000
0#
1'
#15000
b1001000110100 *
b1001000110100 )
b1001000110100 0
b1 (
b1 /
1&
1#
#20000
0#
#25000
b1001000110100 "
b1001000110100 2
b1 $
b1 -
0&
1#
#26000
b10 %
b10 .
#30000
0#
#35000
b101011001111000 !
b101011001111000 1
b101011001111000 )
b101011001111000 0
b10 (
b10 /
1&
1#
#40000
0#
#45000
0&
1#
#50000
0#
#55000
b1010101010101010 )
b1010101010101010 0
b0 (
b0 /
1&
1#
#60000
0#
#65000
b0 "
b0 2
b0 $
b0 -
0&
1#
