rtl/isa_defs.vh
// архитектура набора команд
`ifndef ISA_DEFS_VH
`define ISA_DEFS_VH

`define OP_ADD   4'b0001
`define OP_SUB   4'b0010
`define OP_AND   4'b0011
`define OP_OR    4'b0100
`define OP_LOAD  4'b0101
`define OP_STORE 4'b0110
`define OP_LDI   4'b0111
`define OP_JUMP  4'b1000
`define OP_BEQ   4'b1001
`define OP_XOR   4'b1010
`define OP_NOT   4'b1011

`define ALU_ADD    4'b0001
`define ALU_SUB    4'b0010
`define ALU_AND    4'b0011
`define ALU_OR     4'b0100
`define ALU_XOR    4'b1010
`define ALU_NOT    4'b1011
`define ALU_PASS_A 4'b1100
`define ALU_PASS_B 4'b1101

`endif

rtl/control_unit.v
// Файл: rtl/control_unit.v
`include "isa_defs.vh"

module control_unit (
    input  wire        clk,
    input  wire        rst_n,
    input  wire [15:0] instruction,  // Текущая команда из instr_mem
    input  wire        zero_flag,    // Флаг из АЛУ
    // Управляющие сигналы для Data Path
    output reg         pc_load,
    output reg  [15:0] pc_next,
    output reg         reg_write,
    output reg         mem_write,
    output reg  [3:0]  alu_op,
    output reg         alu_src_b_sel, // Выбор между регистром и Immediate
    output reg  [1:0]  state_debug
);
    localparam FETCH_STATE   = 2'b00;
    localparam EXECUTE_STATE = 2'b01;

    wire [3:0] opcode = instruction[15:12];

    // Регистр состояний FSM (переходы Moore: только от текущего state)
    always @(posedge clk or negedge rst_n) begin
        if (!rst_n)
            state_debug <= FETCH_STATE;
        else if (state_debug == FETCH_STATE)
            state_debug <= EXECUTE_STATE;
        else
            state_debug <= FETCH_STATE;
    end

    // Комбинационная логика выходов (Mealy: opcode, zero_flag; см. PROJECT_REQUIREMENTS_COMPLIANCE.txt)
    always @(*) begin
        pc_load = 1'b0;
        pc_next = 16'd0;
        reg_write = 1'b0;
        mem_write = 1'b0;
        alu_op = `ALU_ADD;
        alu_src_b_sel = 1'b0;

        case (opcode)
            `OP_ADD: begin
                reg_write = 1'b1;
                alu_op = `ALU_ADD;
            end
            `OP_SUB: begin
                reg_write = 1'b1;
                alu_op = `ALU_SUB;
            end
            `OP_AND: begin
                reg_write = 1'b1;
                alu_op = `ALU_AND;
            end
            `OP_OR: begin
                reg_write = 1'b1;
                alu_op = `ALU_OR;
            end
            `OP_XOR: begin
                reg_write = 1'b1;
                alu_op = `ALU_XOR;
            end
            `OP_NOT: begin
                reg_write = 1'b1;
                alu_op = `ALU_NOT;
            end
            `OP_LOAD: begin
                reg_write = 1'b1;
                alu_op = `ALU_ADD;
                alu_src_b_sel = 1'b1;
            end
            `OP_STORE: begin
                mem_write = 1'b1;
                alu_op = `ALU_ADD;
                alu_src_b_sel = 1'b1;
            end
            `OP_LDI: begin
                reg_write = 1'b1;
                alu_op = `ALU_PASS_B;
            end
            `OP_JUMP: begin
                pc_load = 1'b1;
                pc_next = {4'd0, instruction[11:0]};
            end
            `OP_BEQ: begin
                if (zero_flag) begin
                    pc_load = 1'b1;
                    pc_next = {4'd0, instruction[11:0]};
                end
            end
            default: begin
                // NOP
            end
        endcase
    end

endmodule

rtl/data_mem.v
// Файл: rtl/data_mem.v
module data_memory (
    input  wire        clk,
    input  wire        mem_write,     // Сигнал записи от FSM
    input  wire [15:0] addr,          // Адрес (обычно из ALU result)
    input  wire [15:0] write_data,    // Данные из регистрового файла
    output wire [15:0] read_data      // Данные для загрузки в регистр
);

    reg [15:0] ram [0:255];
    integer i;

    initial begin
        for (i = 0; i < 256; i = i + 1)
            ram[i] = 16'h0000;
    end

    // Синхронная запись
    always @(posedge clk) begin
        if (mem_write) // пишем в память
            ram[addr] <= write_data;
    end
    
    // Асинхронное чтение (или синхронное – зависит от реализации)
    assign read_data = ram[addr];

    // Пробный сигнал для VCD/GTKWave (ячейка RAM[1] из тестовой программы)
    wire [15:0] dbg_ram1 = ram[1];

endmodule

rtl/alu.v
// Файл: rtl/alu.v
`include "isa_defs.vh"

module alu (
    input  wire [15:0] a,
    input  wire [15:0] b,
    input  wire [3:0]  alu_op,      // Операция (opcode или производный от него)
    output reg  [15:0] result,
    output wire        zero_flag
);

    always @(*) begin
        case (alu_op)
            `ALU_ADD:    result = a + b;
            `ALU_SUB:    result = a - b;
            `ALU_AND:    result = a & b;
            `ALU_OR:     result = a | b;
            `ALU_XOR:    result = a ^ b;
            `ALU_NOT:    result = ~a;
            `ALU_PASS_A: result = a;
            `ALU_PASS_B: result = b;
            default:     result = 16'd0;
        endcase
    end

    assign zero_flag = (result == 16'd0);

endmodule

rtl/reg_file.v
// Файл: rtl/reg_file.v
module register_file (
    input  wire        clk,
    input  wire        rst_n,
    input  wire        reg_write,        // Разрешение записи (от FSM)
    input  wire [2:0]  read_addr1,       // Адрес первого операнда (SR1)
    input  wire [2:0]  read_addr2,       // Адрес второго операнда (SR2)
    input  wire [2:0]  write_addr,       // Адрес для записи (DR)
    input  wire [15:0] write_data,       // Данные для записи
    output wire [15:0] read_data1,       // Значение первого операнда
    output wire [15:0] read_data2        // Значение второго операнда
);

    // Память регистров (8 x 16 бит)
    reg [15:0] registers [0:7];
    
    // Запись (синхронная)
    always @(posedge clk or negedge rst_n) begin
        if (!rst_n) begin
            // Сброс всех регистров (можно обнулить, но R0 всегда 0 аппаратно)
            integer i;
            for (i = 0; i < 8; i = i + 1)
                registers[i] <= 16'd0;
        end else if (reg_write && write_addr != 3'd0) begin
            // Запрещаем запись в R0
            registers[write_addr] <= write_data;
        end
    end
    
    // Чтение (асинхронное, комбинационное)
    assign read_data1 = (read_addr1 == 3'd0) ? 16'd0 : registers[read_addr1];
    assign read_data2 = (read_addr2 == 3'd0) ? 16'd0 : registers[read_addr2];

    // Пробные сигналы для VCD/GTKWave (массив registers в .vcd не всегда виден)
    wire [15:0] dbg_r1 = registers[1];
    wire [15:0] dbg_r3 = registers[3];
    wire [15:0] dbg_r7 = registers[7];

endmodule

rtl/instr_mem.v
// Файл: rtl/instr_mem.v
module instruction_memory (
    input  wire [15:0] addr,
    output reg  [15:0] instr
);

    reg [15:0] rom [0:255];
    integer i;

    initial begin
        for (i = 0; i < 256; i = i + 1)
            rom[i] = 16'h0000;
`ifdef PROGRAM_HEX_FILE
        $readmemh(`PROGRAM_HEX_FILE, rom);
`elsif QUARTUS_SYNTH
        // Quartus: cwd = quartus/top_cpu_quartus/
        $readmemh("../../tb/program.hex", rom);
`else
        // Icarus: cwd = корень verilogProject/
        $readmemh("tb/program.hex", rom);
`endif
    end

    always @(*) begin
        instr = rom[addr];
    end

endmodule

rtl/pc.v
// Файл: rtl/pc.v
module program_counter (
    input  wire        clk,
    input  wire        rst_n,      // Асинхронный сброс (активный 0)
    input  wire        pc_load,    // Сигнал загрузки нового адреса (от FSM)
    input  wire [15:0] pc_next,    // Новый адрес перехода
    output reg  [15:0] pc_current  // Текущий адрес команды
);

    // Асинхронный сброс, синхронное обновление
    always @(posedge clk or negedge rst_n) begin
        if (!rst_n) // если rst_n = 0, сброс счетчика команд. rst = reset
            pc_current <= 16'h0000;   // Старт с адреса 0
        else if (pc_load)
            pc_current <= pc_next;
        else
            pc_current <= pc_current + 16'd1; // Линейное выполнение
    end

endmodule

rtl/top_cpu.v
// Файл: rtl/top_cpu.v
`include "isa_defs.vh"

module top_cpu (
    input  wire        clk,
    input  wire        rst_n,
    // Для наблюдения за работой (опционально)
    output wire [15:0] pc_out,
    output wire [15:0] instr_out,
    output wire [1:0]  state_out
);

    wire [15:0] pc_current, pc_next_val;
    wire        pc_load_sig;
    wire [15:0] instruction;
    wire [3:0]  opcode;
    wire [2:0]  dr, sr1, sr2;
    wire [2:0]  read_addr2_sel;
    wire [3:0]  alu_op;
    wire        reg_write, mem_write;
    wire        alu_src_b_sel;
    wire [15:0] read_data1, read_data2, alu_result, mem_read_data;
    wire [15:0] alu_b_input;
    wire [15:0] write_data_to_reg;
    wire [15:0] imm6_ext;
    wire [15:0] imm9_ext;
    wire        zero_flag_comb;
    reg         zero_flag_reg;

    assign opcode = instruction[15:12];
    assign dr  = instruction[11:9];
    assign sr1 = instruction[8:6];
    assign sr2 = instruction[5:3];
    assign read_addr2_sel = (opcode == `OP_STORE) ? dr : sr2;
    assign imm6_ext = {{10{instruction[5]}}, instruction[5:0]};
    assign imm9_ext = {{7{instruction[8]}}, instruction[8:0]};
    assign alu_b_input = (opcode == `OP_LDI) ? imm9_ext :
                         (alu_src_b_sel ? imm6_ext : read_data2);

    program_counter pc (
        .clk(clk), .rst_n(rst_n),
        .pc_load(pc_load_sig), .pc_next(pc_next_val),
        .pc_current(pc_current)
    );

    instruction_memory imem (
        .addr(pc_current), .instr(instruction)
    );

    register_file regfile (
        .clk(clk), .rst_n(rst_n),
        .reg_write(reg_write),
        .read_addr1(sr1), .read_addr2(read_addr2_sel),
        .write_addr(dr), .write_data(write_data_to_reg),
        .read_data1(read_data1), .read_data2(read_data2)
    );

    alu alu_unit (
        .a(read_data1), .b(alu_b_input), .alu_op(alu_op),
        .result(alu_result), .zero_flag(zero_flag_comb)
    );

    data_memory dmem (
        .clk(clk),
        .mem_write(mem_write),
        .addr(alu_result),          // Адрес для LOAD/STORE из АЛУ
        .write_data(read_data2),    // Данные для записи из второго регистра
        .read_data(mem_read_data)
    );

    control_unit ctrl (
        .clk(clk), .rst_n(rst_n),
        .instruction(instruction),
        .zero_flag(zero_flag_reg),
        .pc_load(pc_load_sig), .pc_next(pc_next_val),
        .reg_write(reg_write), .mem_write(mem_write),
        .alu_op(alu_op), .alu_src_b_sel(alu_src_b_sel),
        .state_debug(state_out)
    );

    assign write_data_to_reg = (opcode == `OP_LOAD) ? mem_read_data :
                               (opcode == `OP_LDI)  ? imm9_ext :
                               alu_result;

    always @(posedge clk or negedge rst_n) begin
        if (!rst_n) begin
            zero_flag_reg <= 1'b0;
        end else begin
            case (opcode)
                `OP_ADD,
                `OP_SUB,
                `OP_AND,
                `OP_OR,
                `OP_XOR,
                `OP_NOT: zero_flag_reg <= zero_flag_comb;
                `OP_LOAD,
                `OP_LDI: zero_flag_reg <= (write_data_to_reg == 16'd0);
                default: zero_flag_reg <= zero_flag_reg;
            endcase
        end
    end

    assign pc_out = pc_current;
    assign instr_out = instruction;

endmodule

tb/tb_top_cpu.v
`timescale 1ns / 1ps
// Full CPU test: sum_series.asm (1+2+...+10 = 55 in R2), ROM from tb/program.hex

module tb_top_cpu;

    reg        clk, rst_n;
    wire [15:0] pc_out, instr_out;
    wire [1:0]  state_out;
    integer errors;
    integer cycle;

    top_cpu uut (
        .clk(clk),
        .rst_n(rst_n),
        .pc_out(pc_out),
        .instr_out(instr_out),
        .state_out(state_out)
    );

    always #5 clk = ~clk;

    initial begin
        $dumpfile("sim/tb_top_cpu.vcd");
        $dumpvars(0, tb_top_cpu);
        $dumpvars(0, uut.regfile.dbg_r1, uut.regfile.dbg_r2, uut.regfile.dbg_r3);

        $display("=== top_cpu: sum_series (1+2+...+10) ===");
        $display("Program: tb/program.hex (from software/sum_series.asm)");

        clk = 0;
        rst_n = 0;
        errors = 0;
        cycle = 0;

        #10;
        rst_n = 1;

        repeat(80) begin
            @(posedge clk);
            #1;
            cycle = cycle + 1;
            if (cycle <= 40 || cycle % 4 == 0)
                $display("[CPU] c=%0d pc=%0d instr=0x%04h R1=%0d R2=%0d R3=%0d",
                         cycle, pc_out, instr_out,
                         uut.regfile.registers[1],
                         uut.regfile.registers[2],
                         uut.regfile.registers[3]);
        end

        if (uut.regfile.registers[2] !== 16'd55) begin
            $error("R2 (sum) expected 55, got %0d", uut.regfile.registers[2]);
            errors = errors + 1;
        end
        if (uut.regfile.registers[1] !== 16'd0) begin
            $error("R1 (counter) expected 0, got %0d", uut.regfile.registers[1]);
            errors = errors + 1;
        end
        if (uut.regfile.registers[3] !== 16'd11) begin
            $error("R3 (i after loop) expected 11, got %0d", uut.regfile.registers[3]);
            errors = errors + 1;
        end
        if (pc_out !== 16'd9) begin
            $error("PC expected halt at address 9, got %0d", pc_out);
            errors = errors + 1;
        end

        if (errors == 0)
            $display("Top-level simulation PASSED (sum_series, R2=55).");
        else
            $display("Top-level simulation FAILED (%0d errors).", errors);

        $finish;
    end

endmodule

sim/tb_top_cpu.vcd
$date
	Wed May 27 20:05:43 2026
$end
$version
	Icarus Verilog
$end
$timescale
	1ps
$end
$scope module tb_top_cpu $end
$var wire 2 ! state_out [1:0] $end
$var wire 16 " pc_out [15:0] $end
$var wire 16 # instr_out [15:0] $end
$var reg 1 $ clk $end
$var reg 1 % rst_n $end
$var integer 32 & cycle [31:0] $end
$var integer 32 ' errors [31:0] $end
$scope module uut $end
$var wire 1 $ clk $end
$var wire 16 ( instr_out [15:0] $end
$var wire 16 ) pc_out [15:0] $end
$var wire 1 % rst_n $end
$var wire 1 * zero_flag_comb $end
$var wire 16 + write_data_to_reg [15:0] $end
$var wire 2 , state_out [1:0] $end
$var wire 3 - sr2 [2:0] $end
$var wire 3 . sr1 [2:0] $end
$var wire 1 / reg_write $end
$var wire 16 0 read_data2 [15:0] $end
$var wire 16 1 read_data1 [15:0] $end
$var wire 3 2 read_addr2_sel [2:0] $end
$var wire 16 3 pc_next_val [15:0] $end
$var wire 1 4 pc_load_sig $end
$var wire 16 5 pc_current [15:0] $end
$var wire 4 6 opcode [3:0] $end
$var wire 1 7 mem_write $end
$var wire 16 8 mem_read_data [15:0] $end
$var wire 16 9 instruction [15:0] $end
$var wire 16 : imm9_ext [15:0] $end
$var wire 16 ; imm6_ext [15:0] $end
$var wire 3 < dr [2:0] $end
$var wire 1 = alu_src_b_sel $end
$var wire 16 > alu_result [15:0] $end
$var wire 4 ? alu_op [3:0] $end
$var wire 16 @ alu_b_input [15:0] $end
$var reg 1 A zero_flag_reg $end
$scope module alu_unit $end
$var wire 16 B b [15:0] $end
$var wire 1 * zero_flag $end
$var wire 4 C alu_op [3:0] $end
$var wire 16 D a [15:0] $end
$var reg 16 E result [15:0] $end
$upscope $end
$scope module ctrl $end
$var wire 1 $ clk $end
$var wire 1 % rst_n $end
$var wire 1 A zero_flag $end
$var wire 4 F opcode [3:0] $end
$var wire 16 G instruction [15:0] $end
$var parameter 2 H EXECUTE_STATE $end
$var parameter 2 I FETCH_STATE $end
$var reg 4 J alu_op [3:0] $end
$var reg 1 = alu_src_b_sel $end
$var reg 1 7 mem_write $end
$var reg 1 4 pc_load $end
$var reg 16 K pc_next [15:0] $end
$var reg 1 / reg_write $end
$var reg 2 L state_debug [1:0] $end
$upscope $end
$scope module dmem $end
$var wire 16 M addr [15:0] $end
$var wire 1 $ clk $end
$var wire 16 N dbg_ram1 [15:0] $end
$var wire 1 7 mem_write $end
$var wire 16 O read_data [15:0] $end
$var wire 16 P write_data [15:0] $end
$var integer 32 Q i [31:0] $end
$upscope $end
$scope module imem $end
$var wire 16 R addr [15:0] $end
$var reg 16 S instr [15:0] $end
$var integer 32 T i [31:0] $end
$upscope $end
$scope module pc $end
$var wire 1 $ clk $end
$var wire 1 4 pc_load $end
$var wire 16 U pc_next [15:0] $end
$var wire 1 % rst_n $end
$var reg 16 V pc_current [15:0] $end
$upscope $end
$scope module regfile $end
$var wire 1 $ clk $end
$var wire 16 W dbg_r1 [15:0] $end
$var wire 16 X dbg_r3 [15:0] $end
$var wire 16 Y dbg_r7 [15:0] $end
$var wire 3 Z read_addr1 [2:0] $end
$var wire 3 [ read_addr2 [2:0] $end
$var wire 1 / reg_write $end
$var wire 1 % rst_n $end
$var wire 3 \ write_addr [2:0] $end
$var wire 16 ] write_data [15:0] $end
$var wire 16 ^ read_data2 [15:0] $end
$var wire 16 _ read_data1 [15:0] $end
$scope begin $unm_blk_34 $end
$var integer 32 ` i [31:0] $end
$upscope $end
$upscope $end
$upscope $end
$upscope $end
$enddefinitions $end
$comment Show the parameter values. $end
$dumpall
b0 I
b1 H
$end
#0
$dumpvars
b1000 `
b0 _
b0 ^
b101 ]
b1 \
b0 [
b0 Z
b0 Y
b0 X
b0 W
b0 V
b0 U
b100000000 T
b111001000000101 S
b0 R
b100000000 Q
b0 P
b0 O
b0 N
b101 M
b0 L
b0 K
b1101 J
b111001000000101 G
b111 F
b101 E
b0 D
b1101 C
b101 B
0A
b101 @
b1101 ?
b101 >
0=
b1 <
b101 ;
b101 :
b111001000000101 9
b0 8
07
b111 6
b0 5
04
b0 3
b0 2
b0 1
b0 0
1/
b0 .
b0 -
b0 ,
b101 +
0*
b0 )
b111001000000101 (
b0 '
b0 &
0%
0$
b111001000000101 #
b0 "
b0 !
$end
#5000
b1000 `
1$
#10000
0$
1%
#15000
b11 >
b11 E
b11 M
b11 +
b11 ]
b11 @
b11 B
b11 :
b11 ;
b10 <
b10 \
b1101 ?
b1101 C
b1101 J
1/
b111010000000011 #
b111010000000011 (
b111010000000011 9
b111010000000011 G
b111010000000011 S
b1 "
b1 )
b1 5
b1 R
b1 V
b1 !
b1 ,
b1 L
b101 W
1$
#16000
b1 &
#20000
0$
#25000
b1000 +
b1000 ]
b11 0
b11 P
b11 ^
b1000 >
b1000 E
b1000 M
b10 2
b10 [
b101 1
b101 D
b101 _
b11 @
b11 B
b1 F
b1010000 :
b10000 ;
b10 -
b1 .
b1 Z
b11 <
b11 \
b1 6
b1 ?
b1 C
b1 J
1/
b1011001010000 #
b1011001010000 (
b1011001010000 9
b1011001010000 G
b1011001010000 S
b0 !
b0 ,
b0 L
b10 "
b10 )
b10 5
b10 R
b10 V
1$
#26000
b10 &
#30000
0$
#35000
b1 +
b1 ]
b1 @
b1 B
b1 >
b1 E
b1 M
b1000 0
b1000 P
b1000 ^
1=
17
b0 1
b0 D
b0 _
b11 2
b11 [
b110 F
b1 :
b1 ;
b0 -
b0 .
b0 Z
b110 6
0/
b110011000000001 #
b110011000000001 (
b110011000000001 9
b110011000000001 G
b110011000000001 S
b11 "
b11 )
b11 5
b11 R
b11 V
b1 !
b1 ,
b1 L
b1000 X
1$
#36000
b11 &
#40000
0$
#45000
b0 0
b0 P
b0 ^
1/
b0 2
b0 [
b1000 +
b1000 ]
b101 F
b100 <
b100 \
b101 6
1=
07
b101100000000001 #
b101100000000001 (
b101100000000001 9
b101100000000001 G
b101100000000001 S
b0 !
b0 ,
b0 L
b100 "
b100 )
b100 5
b100 R
b100 V
b1000 8
b1000 O
b1000 N
1$
#46000
b100 &
#50000
0$
#55000
1*
b1000 0
b1000 P
b1000 ^
b0 8
b0 O
b0 >
b0 E
b0 M
b1000 @
b1000 B
b10 ?
b10 C
b10 J
b11 2
b11 [
b1000 1
b1000 D
b1000 _
b0 +
b0 ]
b10 F
b1111111100011000 :
b11000 ;
b11 -
b100 .
b100 Z
b101 <
b101 \
b10 6
0=
1/
b10101100011000 #
b10101100011000 (
b10101100011000 9
b10101100011000 G
b10101100011000 S
b101 "
b101 )
b101 5
b101 R
b101 V
b1 !
b1 ,
b1 L
1$
#56000
b101 &
#60000
0$
#65000
b101 @
b101 B
b101 +
b101 ]
b101 0
b101 P
b101 ^
0*
b101 >
b101 E
b101 M
b1000 3
b1000 K
b1000 U
14
b1 2
b1 [
b0 1
b0 D
b0 _
b1001 F
b1000 :
b1000 ;
b1 -
b0 .
b0 Z
b0 <
b0 \
b1001 6
b1 ?
b1 C
b1 J
0/
b1001000000001000 #
b1001000000001000 (
b1001000000001000 9
b1001000000001000 G
b1001000000001000 S
1A
b0 !
b0 ,
b0 L
b110 "
b110 )
b110 5
b110 R
b110 V
1$
#66000
b110 &
#70000
0$
#75000
b111 +
b111 ]
b111 >
b111 E
b111 M
b11 @
b11 B
b11 0
b11 P
b11 ^
b100 ?
b100 C
b100 J
1/
b10 2
b10 [
b101 1
b101 D
b101 _
b100 F
b1010000 :
b10000 ;
b10 -
b1 .
b1 Z
b111 <
b111 \
b100 6
b0 3
b0 K
b0 U
04
b100111001010000 #
b100111001010000 (
b100111001010000 9
b100111001010000 G
b100111001010000 S
b1000 "
b1000 )
b1000 5
b1000 R
b1000 V
b1 !
b1 ,
b1 L
1$
#76000
b111 &
#80000
0$
#85000
b101 @
b101 B
b101 +
b101 ]
b101 0
b101 P
b101 ^
b101 >
b101 E
b101 M
b1001 3
b1001 K
b1001 U
14
b1 2
b1 [
b0 1
b0 D
b0 _
b1000 F
b1001 :
b1001 ;
b1 -
b0 .
b0 Z
b0 <
b0 \
b1000 6
b1 ?
b1 C
b1 J
0/
b1000000000001001 #
b1000000000001001 (
b1000000000001001 9
b1000000000001001 G
b1000000000001001 S
b111 Y
0A
b0 !
b0 ,
b0 L
b1001 "
b1001 )
b1001 5
b1001 R
b1001 V
1$
#86000
b1000 &
#90000
0$
#95000
b1 !
b1 ,
b1 L
1$
#96000
b1001 &
#100000
0$
#105000
b0 !
b0 ,
b0 L
1$
#106000
b1010 &
#110000
0$
#115000
b1 !
b1 ,
b1 L
1$
#116000
b1011 &
#120000
0$
#125000
b0 !
b0 ,
b0 L
1$
#126000
b1100 &
#130000
0$
#135000
b1 !
b1 ,
b1 L
1$
#136000
b1101 &
#140000
0$
#145000
b0 !
b0 ,
b0 L
1$
#146000
b1110 &
#150000
0$
#155000
b1 !
b1 ,
b1 L
1$
#156000
b1111 &
#160000
0$
#165000
b0 !
b0 ,
b0 L
1$
#166000
b10000 &
